[
    {
        "type": 1,
        "content": "2007年10月24日，我国自主研制的第一个月球探测器——嫦娥一号卫星发射成功。该图《中国探月》是中国月球探测工程形象标识，它蕴含着丰富的历史信息，对其解读正确的有：①它是中国汉字②它是中国书法③它反映了中国汉字的象形特征④它反映了中国汉字由繁到简的演变趋势",
        "options": [
            "A．②③④",
            "B．①②③",
            "C．①②④",
            "D．②③④"
        ],
        "answer": 2
    },
    {
        "type": 1,
        "content": "徽剧与汉剧相互融合，兼收昆曲、秦腔以及其他民间曲调的唱腔、剧目和表演方式，形成了一个新剧种：",
        "options": [
            "A．黄梅戏",
            "B．元杂剧",
            "C．京剧",
            "D．粤剧"
        ],
        "answer": 3
    },
    {
        "type": 1,
        "content": "公元前453年，由三名贵族组成的罗马考察团前往希腊，经过近一年的考察，认为雅典的政治制度是“外观的民主，实质的独裁”。这种说法的主要理由是",
        "options": [
            "A．雅典的民主制度是一种直接民主制",
            "B．广大妇女不能参加城邦的公民大会",
            "C．向雅典城邦纳税的外邦人无选举权",
            "D．城邦的实权掌握在少数奴隶主手中"
        ],
        "answer": 4
    },
    {
        "type": 1,
        "content": "罗马法博大而缜密，对人类文明的影响深远。下列叙述正确的是①罗马法是现代欧洲大陆法系的基础 ②法国《民法典》就是以罗马法的有关内容为蓝本起草的 ③现在许多国家的陪审、法律制度和诉讼原则等源于罗马法 ④罗马法是现代资本主义法制的先声，促进了世界资本主义的发展",
        "options": [
            "A．①②③④",
            "B．①②③",
            "C．①②④",
            "D．②③④"
        ],
        "answer": 1
    },
    {
        "type": 1,
        "content": "1520年，一位萨克森商人在里斯本买了许多玉米。回去赚了大钱。他说，我要感谢上帝……，另一位商人说，你还要感谢(   )",
        "options": [
            "A．欧洲一些特色农业区的资本家种出了玉米",
            "B．葡萄牙商人从摩洛哥运回了玉米",
            "C．阿拉伯人从非洲运回了玉米",
            "D．西班牙人从美洲运来了玉米"
        ],
        "answer": 4
    },
    {
        "type": 1,
        "content": "英国人麦考利1830年说：“如今我们国家比1790年还穷吗？我们坚决相信，尽管统治者有种种管理不当之处，但英国一直在变得越来越富。有时略有停顿，有时暂时倒退，但总的趋势是不容置疑的。”这一说法的主要历史背景是(   )",
        "options": [
            "A．国际局势平稳发展",
            "B．资本主义世界市场形成",
            "C．工业革命成效显著",
            "D．西方殖民主义体系确立"
        ],
        "answer": 3
    },
    {
        "type": 1,
        "content": "美国波士顿美术馆馆藏数以万计的中国陶瓷，包括晋代越窑、宋代五大名窑、元明清时期官窑和民窑的陶瓷精品。由此可以推断(   )",
        "options": [
            "A．从晋代起，中美就有了陶瓷贸易",
            "B．上述藏品都是从中国掠夺来的",
            "C．收藏者青睐中国的传统文化艺术",
            "D．中国陶瓷成为该馆的镇馆之宝"
        ],
        "answer": 3
    },
    {
        "type": 1,
        "content": "16世纪初，意大利的威尼斯商入到东地中海组织货源，但发现已经没有什么香料了，而葡萄牙首都里斯本却成为东方商品的仓库。葡萄牙在印度购买一公担胡椒不到3杜卡特，在里斯本却以40杜卡特出售，下列对此表述正确的是(   )①葡萄牙人已经找到通往东方的航路②欧洲的商路和贸易中心从地中海转移到大西洋沿岸③促进了西、葡两国资本主义的发展④西、葡的封建主获取了暴利",
        "options": [
            "A．①②④",
            "B．①②③",
            "C．①③④",
            "D．②③④"
        ],
        "answer": 1
    },
    {
        "type": 1,
        "content": "英国人麦考利1830年说：“如今我们国家比1790年还穷吗？我们坚决相信，尽管统治者有种种管理不当之处，但英国一直在变得越来越富。有时略有停顿，有时暂时倒退，但总的趋势是不容置疑的。”这一说法的主要历史背景是",
        "options": [
            "A．国际局势平稳发展",
            "B．资本主义世界市场形成",
            "C．工业革命成效显著",
            "D．西方殖民主义体系确立"
        ],
        "answer": 3
    },
    {
        "type": 1,
        "content": "1925年初，土耳其改革者发动对旧式礼拜帽的批判，引起了社会上得强烈不满，但欧式帽还是在土耳其流行起来。在百姓中最流行的是鸭舌帽，因为在做礼拜时可以把帽舌反过来朝后戴，前额依旧可以贴在地上。这种现象反映了     （   ）",
        "options": [
            "A．现代与传统之间的一种妥协",
            "B．现代是假，传统是真",
            "C．传统是假，现代是真",
            "D．百姓被迫戴鸭舌帽并"
        ],
        "answer": 1
    }
]